frscript-8.0.0.dist-info/licenses/LICENSE
runtime/Makefile
runtime/__init__.py
runtime/vm.c
src/__init__.py
src/_version.py
src/binary.py
src/builtin_funcs.py
src/cli.py
src/compiler.py
src/debug_runtime.py
src/optimizer.py
src/parser.py
src/run_single_test.py
src/runtime.py
src/tests.py
src/utils.py
frscript-8.0.0.dist-info/METADATA
frscript-8.0.0.dist-info/WHEEL
frscript-8.0.0.dist-info/entry_points.txt
frscript-8.0.0.dist-info/top_level.txt
frscript-8.0.0.dist-info/RECORD
