Metadata-Version: 2.4
Name: frscript
Version: 8.0.0
Summary: Simple bytecode compiled C-style scripting language
Author: Omena0
License: PolyForm Noncommercial License 1.0.0
Project-URL: Source, https://github.com/Omena0/fr
Project-URL: Bug Reports, https://github.com/Omena0/fr/issues
Keywords: compiler,interpreter,scripting,bytecode,language
Classifier: Development Status :: 4 - Beta
Classifier: Intended Audience :: Developers
Classifier: Topic :: Software Development :: Compilers
Classifier: Topic :: Software Development :: Interpreters
Classifier: Programming Language :: Python :: 3
Classifier: Programming Language :: Python :: 3.13
Requires-Python: >=3.13
License-File: LICENSE
Requires-Dist: setuptools
Requires-Dist: zstd
Dynamic: license-file
